{
  "assets/fonts/fontawesome-webfont.eot": {
    "resourceType": "font",
    "mimeType": "font/eot",
    "file": "fontawesome-webfont.7bfcab6d.eot",
    "src": "assets/fonts/fontawesome-webfont.eot"
  },
  "assets/fonts/themify.eot": {
    "resourceType": "font",
    "mimeType": "font/eot",
    "file": "themify.dff415da.eot",
    "src": "assets/fonts/themify.eot"
  },
  "assets/fonts/fontawesome-webfont.woff2": {
    "resourceType": "font",
    "mimeType": "font/woff2",
    "file": "fontawesome-webfont.2adefcbc.woff2",
    "src": "assets/fonts/fontawesome-webfont.woff2"
  },
  "assets/fonts/themify.woff": {
    "resourceType": "font",
    "mimeType": "font/woff",
    "file": "themify.0db5c5a1.woff",
    "src": "assets/fonts/themify.woff"
  },
  "assets/fonts/fontawesome-webfont.woff": {
    "resourceType": "font",
    "mimeType": "font/woff",
    "file": "fontawesome-webfont.ba0c59de.woff",
    "src": "assets/fonts/fontawesome-webfont.woff"
  },
  "assets/fonts/themify.ttf": {
    "resourceType": "font",
    "mimeType": "font/ttf",
    "file": "themify.350663a4.ttf",
    "src": "assets/fonts/themify.ttf"
  },
  "assets/fonts/fontawesome-webfont.ttf": {
    "resourceType": "font",
    "mimeType": "font/ttf",
    "file": "fontawesome-webfont.aa58f33f.ttf",
    "src": "assets/fonts/fontawesome-webfont.ttf"
  },
  "assets/fonts/themify.svg": {
    "resourceType": "image",
    "mimeType": "image/svg+xml",
    "file": "themify.f7af2e09.svg",
    "src": "assets/fonts/themify.svg"
  },
  "assets/fonts/fontawesome-webfont.svg": {
    "resourceType": "image",
    "mimeType": "image/svg+xml",
    "file": "fontawesome-webfont.ad615792.svg",
    "src": "assets/fonts/fontawesome-webfont.svg"
  },
  "node_modules/nuxt/dist/app/entry.mjs": {
    "resourceType": "script",
    "module": true,
    "file": "entry.f9c14453.js",
    "src": "node_modules/nuxt/dist/app/entry.mjs",
    "isEntry": true,
    "dynamicImports": [
      "middleware/auth.js",
      "layouts/custom.vue",
      "layouts/default.vue",
      "virtual:nuxt:/home/sp07/vue/templatian/.nuxt/error-component.mjs"
    ],
    "css": [
      "entry.1273dc3f.css"
    ],
    "assets": [
      "fontawesome-webfont.7bfcab6d.eot",
      "fontawesome-webfont.2adefcbc.woff2",
      "fontawesome-webfont.ba0c59de.woff",
      "fontawesome-webfont.aa58f33f.ttf",
      "fontawesome-webfont.ad615792.svg",
      "themify.dff415da.eot",
      "themify.0db5c5a1.woff",
      "themify.350663a4.ttf",
      "themify.f7af2e09.svg"
    ]
  },
  "entry.1273dc3f.css": {
    "file": "entry.1273dc3f.css",
    "resourceType": "style"
  },
  "fontawesome-webfont.7bfcab6d.eot": {
    "file": "fontawesome-webfont.7bfcab6d.eot",
    "resourceType": "font",
    "mimeType": "font/eot"
  },
  "fontawesome-webfont.2adefcbc.woff2": {
    "file": "fontawesome-webfont.2adefcbc.woff2",
    "resourceType": "font",
    "mimeType": "font/woff2"
  },
  "fontawesome-webfont.ba0c59de.woff": {
    "file": "fontawesome-webfont.ba0c59de.woff",
    "resourceType": "font",
    "mimeType": "font/woff"
  },
  "fontawesome-webfont.aa58f33f.ttf": {
    "file": "fontawesome-webfont.aa58f33f.ttf",
    "resourceType": "font",
    "mimeType": "font/ttf"
  },
  "fontawesome-webfont.ad615792.svg": {
    "file": "fontawesome-webfont.ad615792.svg",
    "resourceType": "image",
    "mimeType": "image/svg+xml"
  },
  "themify.dff415da.eot": {
    "file": "themify.dff415da.eot",
    "resourceType": "font",
    "mimeType": "font/eot"
  },
  "themify.0db5c5a1.woff": {
    "file": "themify.0db5c5a1.woff",
    "resourceType": "font",
    "mimeType": "font/woff"
  },
  "themify.350663a4.ttf": {
    "file": "themify.350663a4.ttf",
    "resourceType": "font",
    "mimeType": "font/ttf"
  },
  "themify.f7af2e09.svg": {
    "file": "themify.f7af2e09.svg",
    "resourceType": "image",
    "mimeType": "image/svg+xml"
  },
  "virtual:nuxt:/home/sp07/vue/templatian/.nuxt/error-component.mjs": {
    "resourceType": "script",
    "module": true,
    "file": "error-component.7cff2c23.js",
    "src": "virtual:nuxt:/home/sp07/vue/templatian/.nuxt/error-component.mjs",
    "isDynamicEntry": true,
    "imports": [
      "node_modules/nuxt/dist/app/entry.mjs"
    ],
    "dynamicImports": [
      "node_modules/@nuxt/ui-templates/dist/templates/error-404.vue",
      "node_modules/@nuxt/ui-templates/dist/templates/error-500.vue"
    ]
  },
  "node_modules/nuxt-icon/dist/runtime/Icon.vue": {
    "resourceType": "script",
    "module": true,
    "file": "Icon.ab681dab.js",
    "src": "node_modules/nuxt-icon/dist/runtime/Icon.vue",
    "isDynamicEntry": true,
    "imports": [
      "node_modules/nuxt/dist/app/entry.mjs"
    ],
    "css": []
  },
  "Icon.294af607.css": {
    "file": "Icon.294af607.css",
    "resourceType": "style"
  },
  "pages/blog/blog-detail.vue": {
    "resourceType": "script",
    "module": true,
    "file": "blog-detail.c2b64f29.js",
    "src": "pages/blog/blog-detail.vue",
    "isDynamicEntry": true,
    "imports": [
      "_breadcrumbs.b2a21b81.js",
      "node_modules/nuxt/dist/app/entry.mjs"
    ]
  },
  "_breadcrumbs.b2a21b81.js": {
    "resourceType": "script",
    "module": true,
    "file": "breadcrumbs.b2a21b81.js",
    "imports": [
      "node_modules/nuxt/dist/app/entry.mjs"
    ]
  },
  "pages/blog/blog-nosidebar.vue": {
    "resourceType": "script",
    "module": true,
    "file": "blog-nosidebar.942fd4b9.js",
    "src": "pages/blog/blog-nosidebar.vue",
    "isDynamicEntry": true,
    "imports": [
      "node_modules/nuxt/dist/app/entry.mjs",
      "_blog.f1877297.js",
      "_breadcrumbs.b2a21b81.js"
    ]
  },
  "_blog.f1877297.js": {
    "resourceType": "script",
    "module": true,
    "file": "blog.f1877297.js",
    "imports": [
      "node_modules/nuxt/dist/app/entry.mjs"
    ]
  },
  "pages/collection/full-width.vue": {
    "resourceType": "script",
    "module": true,
    "file": "full-width.4e865e91.js",
    "src": "pages/collection/full-width.vue",
    "isDynamicEntry": true,
    "imports": [
      "node_modules/nuxt/dist/app/entry.mjs",
      "_index.9d4a2080.js",
      "_breadcrumbs.b2a21b81.js",
      "_compare-popup.37a12edd.js",
      "_swiper.min.1c5b84fa.js"
    ]
  },
  "_index.9d4a2080.js": {
    "resourceType": "script",
    "module": true,
    "file": "index.9d4a2080.js",
    "imports": [
      "node_modules/nuxt/dist/app/entry.mjs"
    ]
  },
  "_compare-popup.37a12edd.js": {
    "resourceType": "script",
    "module": true,
    "file": "compare-popup.37a12edd.js",
    "imports": [
      "node_modules/nuxt/dist/app/entry.mjs",
      "_swiper.min.1c5b84fa.js"
    ]
  },
  "_swiper.min.1c5b84fa.js": {
    "resourceType": "script",
    "module": true,
    "file": "swiper.min.1c5b84fa.js",
    "imports": [
      "node_modules/nuxt/dist/app/entry.mjs"
    ],
    "css": [
      "swiper.41606de1.css"
    ]
  },
  "swiper.41606de1.css": {
    "file": "swiper.41606de1.css",
    "resourceType": "style"
  },
  "pages/collection/leftsidebar/[id].vue": {
    "resourceType": "script",
    "module": true,
    "file": "_id_.77c92a31.js",
    "src": "pages/collection/leftsidebar/[id].vue",
    "isDynamicEntry": true,
    "imports": [
      "node_modules/nuxt/dist/app/entry.mjs",
      "_product-box1.32c56939.js",
      "_filter.d7aa44d2.js",
      "_breadcrumbs.b2a21b81.js",
      "_collection-sidebar.ef7f8d82.js",
      "_compare-popup.37a12edd.js",
      "_cart-modal-popup.9a6ad0e5.js",
      "_2.25ea6962.js",
      "_6.eeb7c80f.js",
      "_empty-search.1c1cc13c.js",
      "_swiper.min.1c5b84fa.js",
      "_navigation.min.8f805591.js"
    ]
  },
  "_product-box1.32c56939.js": {
    "resourceType": "script",
    "module": true,
    "file": "product-box1.32c56939.js",
    "imports": [
      "node_modules/nuxt/dist/app/entry.mjs"
    ]
  },
  "_filter.d7aa44d2.js": {
    "resourceType": "script",
    "module": true,
    "file": "filter.d7aa44d2.js",
    "imports": [
      "node_modules/nuxt/dist/app/entry.mjs"
    ]
  },
  "_collection-sidebar.ef7f8d82.js": {
    "resourceType": "script",
    "module": true,
    "file": "collection-sidebar.ef7f8d82.js",
    "imports": [
      "node_modules/nuxt/dist/app/entry.mjs",
      "_swiper.min.1c5b84fa.js",
      "_navigation.min.8f805591.js",
      "_filter.d7aa44d2.js"
    ]
  },
  "_cart-modal-popup.9a6ad0e5.js": {
    "resourceType": "script",
    "module": true,
    "file": "cart-modal-popup.9a6ad0e5.js",
    "imports": [
      "node_modules/nuxt/dist/app/entry.mjs"
    ]
  },
  "_2.25ea6962.js": {
    "resourceType": "script",
    "module": true,
    "file": "2.25ea6962.js"
  },
  "_6.eeb7c80f.js": {
    "resourceType": "script",
    "module": true,
    "file": "6.eeb7c80f.js"
  },
  "_empty-search.1c1cc13c.js": {
    "resourceType": "script",
    "module": true,
    "file": "empty-search.1c1cc13c.js"
  },
  "_navigation.min.8f805591.js": {
    "resourceType": "script",
    "module": true,
    "file": "navigation.min.8f805591.js",
    "imports": [
      "_swiper.min.1c5b84fa.js"
    ],
    "css": [
      "navigation.079e38c4.css"
    ]
  },
  "navigation.079e38c4.css": {
    "file": "navigation.079e38c4.css",
    "resourceType": "style"
  },
  "pages/collection/list-view.vue": {
    "resourceType": "script",
    "module": true,
    "file": "list-view.c0f15c34.js",
    "src": "pages/collection/list-view.vue",
    "isDynamicEntry": true,
    "imports": [
      "node_modules/nuxt/dist/app/entry.mjs",
      "_product-box1.32c56939.js",
      "_filter.d7aa44d2.js",
      "_breadcrumbs.b2a21b81.js",
      "_collection-sidebar.ef7f8d82.js",
      "_compare-popup.37a12edd.js",
      "_cart-modal-popup.9a6ad0e5.js",
      "_2.25ea6962.js",
      "_6.eeb7c80f.js",
      "_swiper.min.1c5b84fa.js",
      "_navigation.min.8f805591.js"
    ]
  },
  "pages/collection/metro.vue": {
    "resourceType": "script",
    "module": true,
    "file": "metro.117c55d2.js",
    "src": "pages/collection/metro.vue",
    "isDynamicEntry": true,
    "imports": [
      "node_modules/nuxt/dist/app/entry.mjs",
      "_2.25ea6962.js",
      "_index.9d4a2080.js",
      "_breadcrumbs.b2a21b81.js",
      "_compare-popup.37a12edd.js",
      "_cart-modal-popup.9a6ad0e5.js",
      "_swiper.min.1c5b84fa.js"
    ]
  },
  "pages/collection/no-sidebar.vue": {
    "resourceType": "script",
    "module": true,
    "file": "no-sidebar.6fc8d4d8.js",
    "src": "pages/collection/no-sidebar.vue",
    "isDynamicEntry": true,
    "imports": [
      "node_modules/nuxt/dist/app/entry.mjs",
      "_product-box1.32c56939.js",
      "_breadcrumbs.b2a21b81.js",
      "_compare-popup.37a12edd.js",
      "_cart-modal-popup.9a6ad0e5.js",
      "_2.25ea6962.js",
      "_6.eeb7c80f.js",
      "_empty-search.1c1cc13c.js",
      "_swiper.min.1c5b84fa.js"
    ]
  },
  "pages/collection/right-sidebar.vue": {
    "resourceType": "script",
    "module": true,
    "file": "right-sidebar.fc3526a5.js",
    "src": "pages/collection/right-sidebar.vue",
    "isDynamicEntry": true,
    "imports": [
      "node_modules/nuxt/dist/app/entry.mjs",
      "_product-box1.32c56939.js",
      "_index.46378ca7.js",
      "_filter.d7aa44d2.js",
      "_breadcrumbs.b2a21b81.js",
      "_collection-sidebar.ef7f8d82.js",
      "_compare-popup.37a12edd.js",
      "_cart-modal-popup.9a6ad0e5.js",
      "_2.25ea6962.js",
      "_6.eeb7c80f.js",
      "_empty-search.1c1cc13c.js",
      "_discover.5287eaca.js",
      "_swiper.min.1c5b84fa.js",
      "_navigation.min.8f805591.js"
    ]
  },
  "_index.46378ca7.js": {
    "resourceType": "script",
    "module": true,
    "file": "index.46378ca7.js",
    "imports": [
      "_discover.5287eaca.js",
      "node_modules/nuxt/dist/app/entry.mjs"
    ]
  },
  "_discover.5287eaca.js": {
    "resourceType": "script",
    "module": true,
    "file": "discover.5287eaca.js"
  },
  "pages/collection/sidebar-popup.vue": {
    "resourceType": "script",
    "module": true,
    "file": "sidebar-popup.485492dc.js",
    "src": "pages/collection/sidebar-popup.vue",
    "isDynamicEntry": true,
    "imports": [
      "node_modules/nuxt/dist/app/entry.mjs",
      "_product-box1.32c56939.js",
      "_filter.d7aa44d2.js",
      "_breadcrumbs.b2a21b81.js",
      "_collection-sidebar.ef7f8d82.js",
      "_compare-popup.37a12edd.js",
      "_cart-modal-popup.9a6ad0e5.js",
      "_2.25ea6962.js",
      "_6.eeb7c80f.js",
      "_empty-search.1c1cc13c.js",
      "_swiper.min.1c5b84fa.js",
      "_navigation.min.8f805591.js"
    ]
  },
  "pages/collection/six-grid.vue": {
    "resourceType": "script",
    "module": true,
    "file": "six-grid.245b5492.js",
    "src": "pages/collection/six-grid.vue",
    "isDynamicEntry": true,
    "imports": [
      "node_modules/nuxt/dist/app/entry.mjs",
      "_product-box1.32c56939.js",
      "_filter.d7aa44d2.js",
      "_breadcrumbs.b2a21b81.js",
      "_collection-sidebar.ef7f8d82.js",
      "_compare-popup.37a12edd.js",
      "_cart-modal-popup.9a6ad0e5.js",
      "_2.25ea6962.js",
      "_6.eeb7c80f.js",
      "_swiper.min.1c5b84fa.js",
      "_navigation.min.8f805591.js"
    ]
  },
  "pages/collection/three-grid.vue": {
    "resourceType": "script",
    "module": true,
    "file": "three-grid.b91b9b35.js",
    "src": "pages/collection/three-grid.vue",
    "isDynamicEntry": true,
    "imports": [
      "node_modules/nuxt/dist/app/entry.mjs",
      "_product-box1.32c56939.js",
      "_index.46378ca7.js",
      "_filter.d7aa44d2.js",
      "_breadcrumbs.b2a21b81.js",
      "_collection-sidebar.ef7f8d82.js",
      "_compare-popup.37a12edd.js",
      "_cart-modal-popup.9a6ad0e5.js",
      "_2.25ea6962.js",
      "_discover.5287eaca.js",
      "_swiper.min.1c5b84fa.js",
      "_navigation.min.8f805591.js"
    ]
  },
  "pages/index.vue": {
    "resourceType": "script",
    "module": true,
    "file": "index.5c1f9071.js",
    "src": "pages/index.vue",
    "isDynamicEntry": true,
    "imports": [
      "pages/shop/beauty/index.vue",
      "node_modules/nuxt/dist/app/entry.mjs",
      "_blog.f1877297.js",
      "_compare-popup.37a12edd.js",
      "_swiper.min.1c5b84fa.js",
      "_cart-modal-popup.9a6ad0e5.js",
      "_navigation.min.8f805591.js",
      "_product-box1.32c56939.js"
    ]
  },
  "pages/shop/beauty/index.vue": {
    "resourceType": "script",
    "module": true,
    "file": "index.fd78208b.js",
    "src": "pages/shop/beauty/index.vue",
    "isDynamicEntry": true,
    "imports": [
      "node_modules/nuxt/dist/app/entry.mjs",
      "_blog.f1877297.js",
      "_compare-popup.37a12edd.js",
      "_cart-modal-popup.9a6ad0e5.js",
      "_swiper.min.1c5b84fa.js",
      "_navigation.min.8f805591.js",
      "_product-box1.32c56939.js"
    ]
  },
  "pages/page/404.vue": {
    "resourceType": "script",
    "module": true,
    "file": "404.62a6f2be.js",
    "src": "pages/page/404.vue",
    "isDynamicEntry": true,
    "imports": [
      "node_modules/nuxt/dist/app/entry.mjs",
      "_breadcrumbs.b2a21b81.js"
    ]
  },
  "pages/page/about.vue": {
    "resourceType": "script",
    "module": true,
    "file": "about.8603f3d8.js",
    "src": "pages/page/about.vue",
    "isDynamicEntry": true,
    "imports": [
      "_swiper.min.1c5b84fa.js",
      "_breadcrumbs.b2a21b81.js",
      "node_modules/nuxt/dist/app/entry.mjs"
    ]
  },
  "pages/page/account/cart.vue": {
    "resourceType": "script",
    "module": true,
    "file": "cart.967410db.js",
    "src": "pages/page/account/cart.vue",
    "isDynamicEntry": true,
    "imports": [
      "node_modules/nuxt/dist/app/entry.mjs",
      "_breadcrumbs.b2a21b81.js"
    ]
  },
  "pages/page/account/checkout.vue": {
    "resourceType": "script",
    "module": true,
    "file": "checkout.f19b4fd3.js",
    "src": "pages/page/account/checkout.vue",
    "isDynamicEntry": true,
    "imports": [
      "_breadcrumbs.b2a21b81.js",
      "node_modules/nuxt/dist/app/entry.mjs",
      "_cookie.3ac7710e.js"
    ]
  },
  "_cookie.3ac7710e.js": {
    "resourceType": "script",
    "module": true,
    "file": "cookie.3ac7710e.js",
    "imports": [
      "node_modules/nuxt/dist/app/entry.mjs"
    ]
  },
  "pages/page/account/contact.vue": {
    "resourceType": "script",
    "module": true,
    "file": "contact.757dde8b.js",
    "src": "pages/page/account/contact.vue",
    "isDynamicEntry": true,
    "imports": [
      "_breadcrumbs.b2a21b81.js",
      "node_modules/nuxt/dist/app/entry.mjs"
    ]
  },
  "pages/page/account/dashboard.vue": {
    "resourceType": "script",
    "module": true,
    "file": "dashboard.57d69475.js",
    "src": "pages/page/account/dashboard.vue",
    "isDynamicEntry": true,
    "imports": [
      "_breadcrumbs.b2a21b81.js",
      "node_modules/nuxt/dist/app/entry.mjs"
    ]
  },
  "pages/page/account/forget-password.vue": {
    "resourceType": "script",
    "module": true,
    "file": "forget-password.76a26a31.js",
    "src": "pages/page/account/forget-password.vue",
    "isDynamicEntry": true,
    "imports": [
      "_breadcrumbs.b2a21b81.js",
      "node_modules/nuxt/dist/app/entry.mjs"
    ]
  },
  "pages/page/account/login.vue": {
    "resourceType": "script",
    "module": true,
    "file": "login.edd4f202.js",
    "src": "pages/page/account/login.vue",
    "isDynamicEntry": true,
    "imports": [
      "node_modules/nuxt/dist/app/entry.mjs",
      "_breadcrumbs.b2a21b81.js",
      "pages/page/auth/auth.js",
      "_cookie.3ac7710e.js"
    ]
  },
  "pages/page/auth/auth.js": {
    "resourceType": "script",
    "module": true,
    "file": "auth.304e5196.js",
    "src": "pages/page/auth/auth.js",
    "isDynamicEntry": true,
    "imports": [
      "node_modules/nuxt/dist/app/entry.mjs",
      "_cookie.3ac7710e.js"
    ]
  },
  "pages/page/account/profile.vue": {
    "resourceType": "script",
    "module": true,
    "file": "profile.88b610fc.js",
    "src": "pages/page/account/profile.vue",
    "isDynamicEntry": true,
    "imports": [
      "_breadcrumbs.b2a21b81.js",
      "node_modules/nuxt/dist/app/entry.mjs"
    ]
  },
  "pages/page/account/register.vue": {
    "resourceType": "script",
    "module": true,
    "file": "register.584e7e50.js",
    "src": "pages/page/account/register.vue",
    "isDynamicEntry": true,
    "imports": [
      "_breadcrumbs.b2a21b81.js",
      "node_modules/nuxt/dist/app/entry.mjs"
    ]
  },
  "pages/page/account/wishlist.vue": {
    "resourceType": "script",
    "module": true,
    "file": "wishlist.53d4957b.js",
    "src": "pages/page/account/wishlist.vue",
    "isDynamicEntry": true,
    "imports": [
      "node_modules/nuxt/dist/app/entry.mjs",
      "_breadcrumbs.b2a21b81.js"
    ]
  },
  "pages/page/collection.vue": {
    "resourceType": "script",
    "module": true,
    "file": "collection.70bc06ef.js",
    "src": "pages/page/collection.vue",
    "isDynamicEntry": true,
    "imports": [
      "_breadcrumbs.b2a21b81.js",
      "node_modules/nuxt/dist/app/entry.mjs"
    ]
  },
  "pages/page/coming-soon.vue": {
    "resourceType": "script",
    "module": true,
    "file": "coming-soon.bfb21a53.js",
    "src": "pages/page/coming-soon.vue",
    "isDynamicEntry": true,
    "imports": [
      "node_modules/nuxt/dist/app/entry.mjs"
    ]
  },
  "pages/page/compare/compare-1.vue": {
    "resourceType": "script",
    "module": true,
    "file": "compare-1.7ea44da0.js",
    "src": "pages/page/compare/compare-1.vue",
    "isDynamicEntry": true,
    "imports": [
      "node_modules/nuxt/dist/app/entry.mjs",
      "_breadcrumbs.b2a21b81.js",
      "_empty-compare.bed2ff03.js"
    ]
  },
  "_empty-compare.bed2ff03.js": {
    "resourceType": "script",
    "module": true,
    "file": "empty-compare.bed2ff03.js"
  },
  "pages/page/compare/compare-2.vue": {
    "resourceType": "script",
    "module": true,
    "file": "compare-2.b40a775c.js",
    "src": "pages/page/compare/compare-2.vue",
    "isDynamicEntry": true,
    "imports": [
      "node_modules/nuxt/dist/app/entry.mjs",
      "_swiper.min.1c5b84fa.js",
      "_breadcrumbs.b2a21b81.js",
      "_empty-compare.bed2ff03.js"
    ]
  },
  "pages/page/element/banner.vue": {
    "resourceType": "script",
    "module": true,
    "file": "banner.eb7b77ae.js",
    "src": "pages/page/element/banner.vue",
    "isDynamicEntry": true,
    "imports": [
      "_breadcrumbs.b2a21b81.js",
      "_timer.1214a1a8.js",
      "node_modules/nuxt/dist/app/entry.mjs"
    ]
  },
  "_timer.1214a1a8.js": {
    "resourceType": "script",
    "module": true,
    "file": "timer.1214a1a8.js",
    "imports": [
      "node_modules/nuxt/dist/app/entry.mjs"
    ]
  },
  "pages/page/element/category.vue": {
    "resourceType": "script",
    "module": true,
    "file": "category.08ea7b88.js",
    "src": "pages/page/element/category.vue",
    "isDynamicEntry": true,
    "imports": [
      "_swiper.min.1c5b84fa.js",
      "_breadcrumbs.b2a21b81.js",
      "node_modules/nuxt/dist/app/entry.mjs"
    ]
  },
  "pages/page/element/collection-banner.vue": {
    "resourceType": "script",
    "module": true,
    "file": "collection-banner.7c10719f.js",
    "src": "pages/page/element/collection-banner.vue",
    "isDynamicEntry": true,
    "imports": [
      "node_modules/nuxt/dist/app/entry.mjs",
      "_breadcrumbs.b2a21b81.js"
    ]
  },
  "pages/page/element/home-slider.vue": {
    "resourceType": "script",
    "module": true,
    "file": "home-slider.fe162556.js",
    "src": "pages/page/element/home-slider.vue",
    "isDynamicEntry": true,
    "imports": [
      "node_modules/nuxt/dist/app/entry.mjs",
      "_swiper.min.1c5b84fa.js",
      "_navigation.min.8f805591.js",
      "_breadcrumbs.b2a21b81.js"
    ]
  },
  "pages/page/element/logo-slider.vue": {
    "resourceType": "script",
    "module": true,
    "file": "logo-slider.b0f9c355.js",
    "src": "pages/page/element/logo-slider.vue",
    "isDynamicEntry": true,
    "imports": [
      "_swiper.min.1c5b84fa.js",
      "_breadcrumbs.b2a21b81.js",
      "node_modules/nuxt/dist/app/entry.mjs"
    ]
  },
  "pages/page/element/multi-slider.vue": {
    "resourceType": "script",
    "module": true,
    "file": "multi-slider.04dd3e55.js",
    "src": "pages/page/element/multi-slider.vue",
    "isDynamicEntry": true,
    "imports": [
      "node_modules/nuxt/dist/app/entry.mjs",
      "_swiper.min.1c5b84fa.js",
      "_navigation.min.8f805591.js",
      "_breadcrumbs.b2a21b81.js"
    ]
  },
  "pages/page/element/product-slider.vue": {
    "resourceType": "script",
    "module": true,
    "file": "product-slider.b57097e2.js",
    "src": "pages/page/element/product-slider.vue",
    "isDynamicEntry": true,
    "imports": [
      "_product-box1.32c56939.js",
      "node_modules/nuxt/dist/app/entry.mjs",
      "_swiper.min.1c5b84fa.js",
      "_breadcrumbs.b2a21b81.js",
      "_compare-popup.37a12edd.js",
      "_cart-modal-popup.9a6ad0e5.js"
    ]
  },
  "pages/page/element/product-tabs.vue": {
    "resourceType": "script",
    "module": true,
    "file": "product-tabs.5e9b5e43.js",
    "src": "pages/page/element/product-tabs.vue",
    "isDynamicEntry": true,
    "imports": [
      "_product-box1.32c56939.js",
      "node_modules/nuxt/dist/app/entry.mjs",
      "_breadcrumbs.b2a21b81.js",
      "_compare-popup.37a12edd.js",
      "_cart-modal-popup.9a6ad0e5.js",
      "_swiper.min.1c5b84fa.js"
    ]
  },
  "pages/page/element/service.vue": {
    "resourceType": "script",
    "module": true,
    "file": "service.669162aa.js",
    "src": "pages/page/element/service.vue",
    "isDynamicEntry": true,
    "imports": [
      "_breadcrumbs.b2a21b81.js",
      "node_modules/nuxt/dist/app/entry.mjs"
    ]
  },
  "pages/page/faq.vue": {
    "resourceType": "script",
    "module": true,
    "file": "faq.44294c1d.js",
    "src": "pages/page/faq.vue",
    "isDynamicEntry": true,
    "imports": [
      "_breadcrumbs.b2a21b81.js",
      "node_modules/nuxt/dist/app/entry.mjs"
    ]
  },
  "pages/page/lookbook.vue": {
    "resourceType": "script",
    "module": true,
    "file": "lookbook.fe1633c6.js",
    "src": "pages/page/lookbook.vue",
    "isDynamicEntry": true,
    "imports": [
      "_breadcrumbs.b2a21b81.js",
      "node_modules/nuxt/dist/app/entry.mjs"
    ]
  },
  "pages/page/order-success.vue": {
    "resourceType": "script",
    "module": true,
    "file": "order-success.ac9f3966.js",
    "src": "pages/page/order-success.vue",
    "isDynamicEntry": true,
    "imports": [
      "node_modules/nuxt/dist/app/entry.mjs"
    ]
  },
  "pages/page/portfolio/masonary-fullwidth.vue": {
    "resourceType": "script",
    "module": true,
    "file": "masonary-fullwidth.c33528a9.js",
    "src": "pages/page/portfolio/masonary-fullwidth.vue",
    "isDynamicEntry": true,
    "imports": [
      "_index.9d4a2080.js",
      "_breadcrumbs.b2a21b81.js",
      "node_modules/nuxt/dist/app/entry.mjs"
    ]
  },
  "pages/page/portfolio/mesonary-grid-2.vue": {
    "resourceType": "script",
    "module": true,
    "file": "mesonary-grid-2.d25e29b4.js",
    "src": "pages/page/portfolio/mesonary-grid-2.vue",
    "isDynamicEntry": true,
    "imports": [
      "_index.9d4a2080.js",
      "_breadcrumbs.b2a21b81.js",
      "node_modules/nuxt/dist/app/entry.mjs"
    ]
  },
  "pages/page/portfolio/mesonary-grid-3.vue": {
    "resourceType": "script",
    "module": true,
    "file": "mesonary-grid-3.9014c124.js",
    "src": "pages/page/portfolio/mesonary-grid-3.vue",
    "isDynamicEntry": true,
    "imports": [
      "_index.46378ca7.js",
      "_index.9d4a2080.js",
      "_breadcrumbs.b2a21b81.js",
      "node_modules/nuxt/dist/app/entry.mjs",
      "_discover.5287eaca.js"
    ]
  },
  "pages/page/portfolio/mesonary-grid-4.vue": {
    "resourceType": "script",
    "module": true,
    "file": "mesonary-grid-4.8f1f37ac.js",
    "src": "pages/page/portfolio/mesonary-grid-4.vue",
    "isDynamicEntry": true,
    "imports": [
      "_index.46378ca7.js",
      "_index.9d4a2080.js",
      "_breadcrumbs.b2a21b81.js",
      "node_modules/nuxt/dist/app/entry.mjs",
      "_discover.5287eaca.js"
    ]
  },
  "pages/page/portfolio/portfolio-2-col.vue": {
    "resourceType": "script",
    "module": true,
    "file": "portfolio-2-col.78b4599f.js",
    "src": "pages/page/portfolio/portfolio-2-col.vue",
    "isDynamicEntry": true,
    "imports": [
      "_lightBox.5a5ae6a2.js",
      "_breadcrumbs.b2a21b81.js",
      "node_modules/nuxt/dist/app/entry.mjs",
      "_client-only.0965c2e8.js"
    ]
  },
  "_lightBox.5a5ae6a2.js": {
    "resourceType": "script",
    "module": true,
    "file": "lightBox.5a5ae6a2.js",
    "imports": [
      "_client-only.0965c2e8.js",
      "node_modules/nuxt/dist/app/entry.mjs"
    ]
  },
  "_client-only.0965c2e8.js": {
    "resourceType": "script",
    "module": true,
    "file": "client-only.0965c2e8.js",
    "imports": [
      "node_modules/nuxt/dist/app/entry.mjs"
    ]
  },
  "pages/page/portfolio/portfolio-3-col.vue": {
    "resourceType": "script",
    "module": true,
    "file": "portfolio-3-col.d926db8c.js",
    "src": "pages/page/portfolio/portfolio-3-col.vue",
    "isDynamicEntry": true,
    "imports": [
      "_lightBox.5a5ae6a2.js",
      "_breadcrumbs.b2a21b81.js",
      "node_modules/nuxt/dist/app/entry.mjs",
      "_client-only.0965c2e8.js"
    ]
  },
  "pages/page/portfolio/portfolio-4-col.vue": {
    "resourceType": "script",
    "module": true,
    "file": "portfolio-4-col.9af0c454.js",
    "src": "pages/page/portfolio/portfolio-4-col.vue",
    "isDynamicEntry": true,
    "imports": [
      "_lightBox.5a5ae6a2.js",
      "_index.46378ca7.js",
      "_breadcrumbs.b2a21b81.js",
      "node_modules/nuxt/dist/app/entry.mjs",
      "_client-only.0965c2e8.js",
      "_discover.5287eaca.js"
    ]
  },
  "pages/page/review.vue": {
    "resourceType": "script",
    "module": true,
    "file": "review.d8bcb178.js",
    "src": "pages/page/review.vue",
    "isDynamicEntry": true,
    "imports": [
      "_breadcrumbs.b2a21b81.js",
      "node_modules/nuxt/dist/app/entry.mjs"
    ]
  },
  "pages/page/search.vue": {
    "resourceType": "script",
    "module": true,
    "file": "search.0f6c5074.js",
    "src": "pages/page/search.vue",
    "isDynamicEntry": true,
    "imports": [
      "node_modules/nuxt/dist/app/entry.mjs",
      "_product-box1.32c56939.js",
      "_breadcrumbs.b2a21b81.js"
    ]
  },
  "pages/page/sitemap.vue": {
    "resourceType": "script",
    "module": true,
    "file": "sitemap.249bb1e7.js",
    "src": "pages/page/sitemap.vue",
    "isDynamicEntry": true,
    "imports": [
      "node_modules/nuxt/dist/app/entry.mjs"
    ]
  },
  "pages/page/typography.vue": {
    "resourceType": "script",
    "module": true,
    "file": "typography.ab3751ea.js",
    "src": "pages/page/typography.vue",
    "isDynamicEntry": true,
    "imports": [
      "_breadcrumbs.b2a21b81.js",
      "node_modules/nuxt/dist/app/entry.mjs"
    ]
  },
  "pages/product/bundle-product.vue": {
    "resourceType": "script",
    "module": true,
    "file": "bundle-product.d33386ab.js",
    "src": "pages/product/bundle-product.vue",
    "isDynamicEntry": true,
    "imports": [
      "node_modules/nuxt/dist/app/entry.mjs",
      "_swiper.min.1c5b84fa.js",
      "_breadcrumbs.b2a21b81.js",
      "_timer.1214a1a8.js",
      "_size-chart.96c8f01c.js",
      "_product-box1.32c56939.js",
      "_cart-modal-popup.9a6ad0e5.js",
      "_compare-popup.37a12edd.js"
    ]
  },
  "_size-chart.96c8f01c.js": {
    "resourceType": "script",
    "module": true,
    "file": "size-chart.96c8f01c.js",
    "imports": [
      "_product-box1.32c56939.js",
      "node_modules/nuxt/dist/app/entry.mjs",
      "_cart-modal-popup.9a6ad0e5.js",
      "_compare-popup.37a12edd.js"
    ]
  },
  "pages/product/four-image.vue": {
    "resourceType": "script",
    "module": true,
    "file": "four-image.3a0c71c8.js",
    "src": "pages/product/four-image.vue",
    "isDynamicEntry": true,
    "imports": [
      "node_modules/nuxt/dist/app/entry.mjs",
      "_index.46378ca7.js",
      "_breadcrumbs.b2a21b81.js",
      "_timer.1214a1a8.js",
      "_size-chart.96c8f01c.js",
      "_discover.5287eaca.js",
      "_product-box1.32c56939.js",
      "_cart-modal-popup.9a6ad0e5.js",
      "_compare-popup.37a12edd.js",
      "_swiper.min.1c5b84fa.js"
    ]
  },
  "pages/product/sidebar/[id].vue": {
    "resourceType": "script",
    "module": true,
    "file": "_id_.97216837.js",
    "src": "pages/product/sidebar/[id].vue",
    "isDynamicEntry": true,
    "imports": [
      "node_modules/nuxt/dist/app/entry.mjs",
      "_swiper.min.1c5b84fa.js",
      "_breadcrumbs.b2a21b81.js",
      "_timer.1214a1a8.js",
      "_product-sidebar.f8cf406c.js",
      "_size-chart.96c8f01c.js",
      "_navigation.min.8f805591.js",
      "_filter.d7aa44d2.js",
      "_product-box1.32c56939.js",
      "_cart-modal-popup.9a6ad0e5.js",
      "_compare-popup.37a12edd.js"
    ]
  },
  "_product-sidebar.f8cf406c.js": {
    "resourceType": "script",
    "module": true,
    "file": "product-sidebar.f8cf406c.js",
    "imports": [
      "node_modules/nuxt/dist/app/entry.mjs",
      "_swiper.min.1c5b84fa.js",
      "_navigation.min.8f805591.js",
      "_filter.d7aa44d2.js"
    ]
  },
  "pages/product/sidebar/no-sidebar.vue": {
    "resourceType": "script",
    "module": true,
    "file": "no-sidebar.4f10cfe7.js",
    "src": "pages/product/sidebar/no-sidebar.vue",
    "isDynamicEntry": true,
    "imports": [
      "node_modules/nuxt/dist/app/entry.mjs",
      "_swiper.min.1c5b84fa.js",
      "_breadcrumbs.b2a21b81.js",
      "_timer.1214a1a8.js",
      "_size-chart.96c8f01c.js",
      "_product-box1.32c56939.js",
      "_cart-modal-popup.9a6ad0e5.js",
      "_compare-popup.37a12edd.js"
    ]
  },
  "pages/product/sidebar/right-sidebar.vue": {
    "resourceType": "script",
    "module": true,
    "file": "right-sidebar.707cb504.js",
    "src": "pages/product/sidebar/right-sidebar.vue",
    "isDynamicEntry": true,
    "imports": [
      "node_modules/nuxt/dist/app/entry.mjs",
      "_swiper.min.1c5b84fa.js",
      "_breadcrumbs.b2a21b81.js",
      "_timer.1214a1a8.js",
      "_product-sidebar.f8cf406c.js",
      "_size-chart.96c8f01c.js",
      "_navigation.min.8f805591.js",
      "_filter.d7aa44d2.js",
      "_product-box1.32c56939.js",
      "_cart-modal-popup.9a6ad0e5.js",
      "_compare-popup.37a12edd.js"
    ]
  },
  "pages/product/three-column/thumbnail-bottom.vue": {
    "resourceType": "script",
    "module": true,
    "file": "thumbnail-bottom.596eb1b6.js",
    "src": "pages/product/three-column/thumbnail-bottom.vue",
    "isDynamicEntry": true,
    "imports": [
      "node_modules/nuxt/dist/app/entry.mjs",
      "_swiper.min.1c5b84fa.js",
      "_breadcrumbs.b2a21b81.js",
      "_timer.1214a1a8.js",
      "_size-chart.96c8f01c.js",
      "_discover.5287eaca.js",
      "_product-box1.32c56939.js",
      "_cart-modal-popup.9a6ad0e5.js",
      "_compare-popup.37a12edd.js"
    ]
  },
  "pages/product/three-column/thumbnail-left.vue": {
    "resourceType": "script",
    "module": true,
    "file": "thumbnail-left.47230ead.js",
    "src": "pages/product/three-column/thumbnail-left.vue",
    "isDynamicEntry": true,
    "imports": [
      "node_modules/nuxt/dist/app/entry.mjs",
      "_swiper.min.1c5b84fa.js",
      "_breadcrumbs.b2a21b81.js",
      "_timer.1214a1a8.js",
      "_size-chart.96c8f01c.js",
      "_discover.5287eaca.js",
      "_product-box1.32c56939.js",
      "_cart-modal-popup.9a6ad0e5.js",
      "_compare-popup.37a12edd.js"
    ]
  },
  "pages/product/three-column/thumbnail-right.vue": {
    "resourceType": "script",
    "module": true,
    "file": "thumbnail-right.0bd049c7.js",
    "src": "pages/product/three-column/thumbnail-right.vue",
    "isDynamicEntry": true,
    "imports": [
      "node_modules/nuxt/dist/app/entry.mjs",
      "_swiper.min.1c5b84fa.js",
      "_breadcrumbs.b2a21b81.js",
      "_timer.1214a1a8.js",
      "_size-chart.96c8f01c.js",
      "_discover.5287eaca.js",
      "_product-box1.32c56939.js",
      "_cart-modal-popup.9a6ad0e5.js",
      "_compare-popup.37a12edd.js"
    ]
  },
  "pages/product/thumbnail-image/image-outside.vue": {
    "resourceType": "script",
    "module": true,
    "file": "image-outside.95b9b2bc.js",
    "src": "pages/product/thumbnail-image/image-outside.vue",
    "isDynamicEntry": true,
    "imports": [
      "node_modules/nuxt/dist/app/entry.mjs",
      "_swiper.min.1c5b84fa.js",
      "_breadcrumbs.b2a21b81.js",
      "_timer.1214a1a8.js",
      "_size-chart.96c8f01c.js",
      "_product-box1.32c56939.js",
      "_cart-modal-popup.9a6ad0e5.js",
      "_compare-popup.37a12edd.js"
    ]
  },
  "pages/product/thumbnail-image/left-image.vue": {
    "resourceType": "script",
    "module": true,
    "file": "left-image.28fa480e.js",
    "src": "pages/product/thumbnail-image/left-image.vue",
    "isDynamicEntry": true,
    "imports": [
      "node_modules/nuxt/dist/app/entry.mjs",
      "_swiper.min.1c5b84fa.js",
      "_breadcrumbs.b2a21b81.js",
      "_timer.1214a1a8.js",
      "_size-chart.96c8f01c.js",
      "_product-box1.32c56939.js",
      "_cart-modal-popup.9a6ad0e5.js",
      "_compare-popup.37a12edd.js"
    ]
  },
  "pages/product/thumbnail-image/right-image.vue": {
    "resourceType": "script",
    "module": true,
    "file": "right-image.db80f0f4.js",
    "src": "pages/product/thumbnail-image/right-image.vue",
    "isDynamicEntry": true,
    "imports": [
      "node_modules/nuxt/dist/app/entry.mjs",
      "_swiper.min.1c5b84fa.js",
      "_breadcrumbs.b2a21b81.js",
      "_timer.1214a1a8.js",
      "_size-chart.96c8f01c.js",
      "_product-box1.32c56939.js",
      "_cart-modal-popup.9a6ad0e5.js",
      "_compare-popup.37a12edd.js"
    ]
  },
  "middleware/auth.js": {
    "resourceType": "script",
    "module": true,
    "file": "auth.52cf7e4b.js",
    "src": "middleware/auth.js",
    "isDynamicEntry": true
  },
  "layouts/custom.vue": {
    "resourceType": "script",
    "module": true,
    "file": "custom.b5d0f082.js",
    "src": "layouts/custom.vue",
    "isDynamicEntry": true,
    "imports": [
      "_layoutSetting.9d63379b.js",
      "_client-only.0965c2e8.js",
      "node_modules/nuxt/dist/app/entry.mjs"
    ]
  },
  "_layoutSetting.9d63379b.js": {
    "resourceType": "script",
    "module": true,
    "file": "layoutSetting.9d63379b.js",
    "imports": [
      "node_modules/nuxt/dist/app/entry.mjs"
    ]
  },
  "layouts/default.vue": {
    "resourceType": "script",
    "module": true,
    "file": "default.664a4e55.js",
    "src": "layouts/default.vue",
    "isDynamicEntry": true,
    "imports": [
      "node_modules/nuxt/dist/app/entry.mjs",
      "_cookie.3ac7710e.js",
      "pages/page/auth/auth.js",
      "_layoutSetting.9d63379b.js",
      "_client-only.0965c2e8.js",
      "_index.46378ca7.js",
      "_discover.5287eaca.js"
    ],
    "css": [
      "default.86187520.css"
    ]
  },
  "default.86187520.css": {
    "file": "default.86187520.css",
    "resourceType": "style"
  },
  "node_modules/@nuxt/ui-templates/dist/templates/error-404.vue": {
    "resourceType": "script",
    "module": true,
    "file": "error-404.67d75346.js",
    "src": "node_modules/@nuxt/ui-templates/dist/templates/error-404.vue",
    "isDynamicEntry": true,
    "imports": [
      "node_modules/nuxt/dist/app/entry.mjs"
    ],
    "css": []
  },
  "error-404.23f2309d.css": {
    "file": "error-404.23f2309d.css",
    "resourceType": "style"
  },
  "node_modules/@nuxt/ui-templates/dist/templates/error-500.vue": {
    "resourceType": "script",
    "module": true,
    "file": "error-500.c306ef27.js",
    "src": "node_modules/@nuxt/ui-templates/dist/templates/error-500.vue",
    "isDynamicEntry": true,
    "imports": [
      "node_modules/nuxt/dist/app/entry.mjs"
    ],
    "css": []
  },
  "error-500.aa16ed4d.css": {
    "file": "error-500.aa16ed4d.css",
    "resourceType": "style"
  },
  "node_modules/nuxt-icon/dist/runtime/Icon.css": {
    "resourceType": "style",
    "file": "Icon.294af607.css",
    "src": "node_modules/nuxt-icon/dist/runtime/Icon.css"
  },
  "swiper.css": {
    "resourceType": "style",
    "file": "swiper.41606de1.css",
    "src": "swiper.css"
  },
  "navigation.css": {
    "resourceType": "style",
    "file": "navigation.079e38c4.css",
    "src": "navigation.css"
  },
  "node_modules/@nuxt/ui-templates/dist/templates/error-500.css": {
    "resourceType": "style",
    "file": "error-500.aa16ed4d.css",
    "src": "node_modules/@nuxt/ui-templates/dist/templates/error-500.css"
  },
  "layouts/default.css": {
    "resourceType": "style",
    "file": "default.86187520.css",
    "src": "layouts/default.css"
  },
  "node_modules/@nuxt/ui-templates/dist/templates/error-404.css": {
    "resourceType": "style",
    "file": "error-404.23f2309d.css",
    "src": "node_modules/@nuxt/ui-templates/dist/templates/error-404.css"
  },
  "node_modules/nuxt/dist/app/entry.css": {
    "resourceType": "style",
    "file": "entry.1273dc3f.css",
    "src": "node_modules/nuxt/dist/app/entry.css"
  }
}